{
  "products": [
    {
      "id": "1",
      "name": "SUNNIPINDI & OLIVE OIL SOAP",
      "price": 69,
      "description": "Removes dead skin cells, makes skin smooth, soft, and gives a natural glow.",
      "image": "https://encrypted-tbn0.gstatic.com/images?q=tbn:ANd9GcRsEMlt9y3BWJmG33-JogdlIhUhRdfav3JvJg&s",
      "category": "Soap",
      "stock": "in-stock",
      "skinTypes": ["Oily", "Dry"],
      "ingredients": "Sunnipindi, Olive Oil"
    },
    {
      "id": "2",
      "name": "RED SANDAL & OLIVE OIL SOAP",
      "price": 69,
      "description": "Provides skin glow and shine while smoothing texture.",
      "image": "https://www.kappus.com/wp-content/uploads/2021/04/kappus-seife4-2-4.jpg",
      "category": "Soap",
      "stock": "in-stock",
      "skinTypes": ["All Skin Types"],
      "ingredients": "Red Sandalwood, Olive Oil"
    }
  ],
  "orders": [
    {
      "id": "ORD001",
      "user": {
        "name": "John Doe",
        "email": "john@example.com",
        "address": "123 Skin Lane, Glow City"
      },
      "products": [
        { "id": "1", "name": "SUNNIPINDI & OLIVE OIL SOAP", "quantity": 2, "price": 69 }
      ],
      "total": 138,
      "status": "Pending",
      "createdAt": "2026-04-30T10:00:00Z"
    }
  ],
  "users": [
    {
      "id": "U001",
      "name": "John Doe",
      "email": "john@example.com",
      "ordersCount": 1
    }
  ],
  "reviews": [
    {
      "id": "R001",
      "productId": "1",
      "user": "Aanya S.",
      "rating": 5,
      "comment": "My skin texture looks smoother in a week. The ritual feels expensive without being harsh.",
      "status": "approved"
    }
  ],
  "discounts": [],
  "banners": [
    {
      "id": "B1",
      "title": "Transform Your Skin & Hair",
      "subtitle": "Experience the power of natural ingredients",
      "image": "/banner1.jpg",
      "active": true
    }
  ]
}
